.gitignore
CHANGELOG.md
LICENSE
MANIFEST.in
README.md
pyproject.toml
requirements.txt
screenshot.png
setup.cfg
setup.py
.github/ISSUE_TEMPLATE/bug_report.md
.github/ISSUE_TEMPLATE/feature_request.md
.github/ISSUE_TEMPLATE/other--question--discussion--etc--.md
.github/workflows/ci.yml
gpustat/__init__.py
gpustat/__main__.py
gpustat/_shtab.py
gpustat/_version.py
gpustat/cli.py
gpustat/core.py
gpustat/nvml.py
gpustat/test_gpustat.py
gpustat/util.py
gpustat/util_test.py
gpustat.egg-info/PKG-INFO
gpustat.egg-info/SOURCES.txt
gpustat.egg-info/dependency_links.txt
gpustat.egg-info/entry_points.txt
gpustat.egg-info/not-zip-safe
gpustat.egg-info/requires.txt
gpustat.egg-info/top_level.txt