Metadata-Version: 2.1
Name: gpustat
Version: 1.1
Summary: An utility to monitor NVIDIA GPU status and usage
Home-page: https://github.com/wookayin/gpustat
Author: Jongwook Choi
Author-email: wookayin@gmail.com
License: MIT
Keywords: nvidia-smi gpu cuda monitoring gpustat
Classifier: Development Status :: 5 - Production/Stable
Classifier: License :: OSI Approved :: MIT License
Classifier: Operating System :: POSIX :: Linux
Classifier: Programming Language :: Python :: 3.6
Classifier: Programming Language :: Python :: 3.7
Classifier: Programming Language :: Python :: 3.8
Classifier: Programming Language :: Python :: 3.9
Classifier: Programming Language :: Python :: 3.10
Classifier: Programming Language :: Python :: 3.11
Classifier: Topic :: System :: Monitoring
Requires-Python: >=3.6
Provides-Extra: test
Provides-Extra: completion
License-File: LICENSE
